qrhost/__init__.py
qrhost/qrhost.py
qrhost-1.0.4.dist-info/LICENSE
qrhost-1.0.4.dist-info/METADATA
qrhost-1.0.4.dist-info/WHEEL
qrhost-1.0.4.dist-info/entry_points.txt
qrhost-1.0.4.dist-info/top_level.txt
qrhost-1.0.4.dist-info/RECORD
