Metadata-Version: 2.1
Name: qrhost
Version: 1.0.4
Summary: A tool for hosting files and directories with QR codes
Home-page: https://github.com/ryanhamdaoui/qrhost
Author: Hamdaoui Ryan
Author-email: ryanhamdaoui45@gmail.com
License: MIT
Classifier: Programming Language :: Python :: 3
Classifier: License :: OSI Approved :: MIT License
Classifier: Operating System :: OS Independent
Requires-Python: >=3.6
License-File: LICENSE
Requires-Dist: qrcode
Requires-Dist: netifaces
